<?xml version="1.0" encoding="UTF-8"?>
<ListOfCategories xmlns:xsi="http://www.w3.org/2001/XMLSchema-instance" xmlns:xsd="http://www.w3.org/2001/XMLSchema">
  <Category>
    <CategoryName>Top Stories</CategoryName>
    <IsPinned>No</IsPinned>
    <IsGroup>No</IsGroup>
  </Category>

  <Category>
    <CategoryName>Breaking News</CategoryName>
    <IsPinned>No</IsPinned>
    <IsGroup>No</IsGroup>
  </Category>

  <Category>
    <CategoryName>National</CategoryName>
    <IsPinned>No</IsPinned>
    <IsGroup>No</IsGroup>
  </Category>

  <Category>
    <CategoryName>International</CategoryName>
    <IsPinned>No</IsPinned>
    <IsGroup>No</IsGroup>
  </Category>

  <Category>
    <CategoryName>Science and Technology</CategoryName>
    <IsPinned>No</IsPinned>
    <IsGroup>No</IsGroup>
  </Category>

  <Category>
    <CategoryName>Health</CategoryName>
    <IsPinned>No</IsPinned>
    <IsGroup>No</IsGroup>
  </Category>

  <Category>
    <CategoryName>Entertainment</CategoryName>
    <IsPinned>No</IsPinned>
    <IsGroup>No</IsGroup>
  </Category>

  <Category>
    <CategoryName>Sports</CategoryName>
    <IsPinned>No</IsPinned>
    <IsGroup>Yes</IsGroup>
    <Group>
      <Category>
        <CategoryName>Cricket</CategoryName>
        <IsPinned>No</IsPinned>
        <IsGroup>No</IsGroup>
      </Category>
      <Category>
        <CategoryName>Football</CategoryName>
        <IsPinned>No</IsPinned>
        <IsGroup>No</IsGroup>
      </Category>
      <Category>
        <CategoryName>Hockey</CategoryName>
        <IsPinned>No</IsPinned>
        <IsGroup>No</IsGroup>
      </Category>
      <Category>
        <CategoryName>Tennis</CategoryName>
        <IsPinned>No</IsPinned>
        <IsGroup>No</IsGroup>
      </Category>
      <Category>
        <CategoryName>Races</CategoryName>
        <IsPinned>No</IsPinned>
        <IsGroup>No</IsGroup>
      </Category>
    </Group>
  </Category>

  <Category>
    <CategoryName>Features</CategoryName>
    <IsPinned>No</IsPinned>
    <IsGroup>Yes</IsGroup>
    <Group>
      <Category>
        <CategoryName>Friday Review</CategoryName>
        <IsPinned>No</IsPinned>
        <IsGroup>No</IsGroup>
      </Category>
      <Category>
        <CategoryName>Education Plus</CategoryName>
        <IsPinned>No</IsPinned>
        <IsGroup>No</IsGroup>
      </Category>
      <Category>
        <CategoryName>Sunday Magazine</CategoryName>
        <IsPinned>No</IsPinned>
        <IsGroup>No</IsGroup>
      </Category>
      <Category>
        <CategoryName>Cinema Plus</CategoryName>
        <IsPinned>No</IsPinned>
        <IsGroup>No</IsGroup>
      </Category>
      <Category>
        <CategoryName>Habitat</CategoryName>
        <IsPinned>No</IsPinned>
        <IsGroup>No</IsGroup>
      </Category>
      <Category>
        <CategoryName>Metro Plus</CategoryName>
        <IsPinned>No</IsPinned>
        <IsGroup>No</IsGroup>
      </Category>
    </Group>
  </Category>

  <Category>
    <CategoryName>Business</CategoryName>
    <IsPinned>No</IsPinned>
    <IsGroup>Yes</IsGroup>
    <Group>
      <Category>
        <CategoryName>Industry</CategoryName>
        <IsPinned>No</IsPinned>
        <IsGroup>No</IsGroup>
      </Category>
      <Category>
        <CategoryName>Economy</CategoryName>
        <IsPinned>No</IsPinned>
        <IsGroup>No</IsGroup>
      </Category>
      <Category>
        <CategoryName>Market</CategoryName>
        <IsPinned>No</IsPinned>
        <IsGroup>No</IsGroup>
      </Category>
    </Group>
  </Category>

  <Category>
    <CategoryName>Opinion</CategoryName>
    <IsPinned>No</IsPinned>
    <IsGroup>Yes</IsGroup>
    <Group>
      <Category>
        <CategoryName>Lead</CategoryName>
        <IsPinned>No</IsPinned>
        <IsGroup>No</IsGroup>
      </Category>
      <Category>
        <CategoryName>Editorial</CategoryName>
        <IsPinned>No</IsPinned>
        <IsGroup>No</IsGroup>
      </Category>
      <Category>
        <CategoryName>Op-Ed</CategoryName>
        <IsPinned>No</IsPinned>
        <IsGroup>No</IsGroup>
      </Category>
      <Category>
        <CategoryName>Blogs</CategoryName>
        <IsPinned>No</IsPinned>
        <IsGroup>No</IsGroup>
      </Category>
    </Group>
  </Category>

  <Category>
    <CategoryName>Cities</CategoryName>
    <IsPinned>No</IsPinned>
    <IsGroup>Yes</IsGroup>
    <Group>
      <Category>
        <CategoryName>Chennai</CategoryName>
        <IsPinned>No</IsPinned>
        <IsGroup>No</IsGroup>
      </Category>
      <Category>
        <CategoryName>Bengaluru</CategoryName>
        <IsPinned>No</IsPinned>
        <IsGroup>No</IsGroup>
      </Category>
      <Category>
        <CategoryName>Delhi</CategoryName>
        <IsPinned>No</IsPinned>
        <IsGroup>No</IsGroup>
      </Category>
      <Category>
        <CategoryName>Mumbai</CategoryName>
        <IsPinned>No</IsPinned>
        <IsGroup>No</IsGroup>
      </Category>
      <Category>
        <CategoryName>Hyderabad</CategoryName>
        <IsPinned>No</IsPinned>
        <IsGroup>No</IsGroup>
      </Category>
      <Category>
        <CategoryName>Thiruvananthapuram</CategoryName>
        <IsPinned>No</IsPinned>
        <IsGroup>No</IsGroup>
      </Category>
      <Category>
        <CategoryName>Kochi</CategoryName>
        <IsPinned>No</IsPinned>
        <IsGroup>No</IsGroup>
      </Category>
      <Category>
        <CategoryName>Madurai</CategoryName>
        <IsPinned>No</IsPinned>
        <IsGroup>No</IsGroup>
      </Category>
      <Category>
        <CategoryName>Puducherry</CategoryName>
        <IsPinned>No</IsPinned>
        <IsGroup>No</IsGroup>
      </Category>
      <Category>
        <CategoryName>Mangaluru</CategoryName>
        <IsPinned>No</IsPinned>
        <IsGroup>No</IsGroup>
      </Category>
      <Category>
        <CategoryName>Coimbatore</CategoryName>
        <IsPinned>No</IsPinned>
        <IsGroup>No</IsGroup>
      </Category>
      <Category>
        <CategoryName>Vishakapatnam</CategoryName>
        <IsPinned>No</IsPinned>
        <IsGroup>No</IsGroup>
      </Category>
      <Category>
        <CategoryName>Vijayawada</CategoryName>
        <IsPinned>No</IsPinned>
        <IsGroup>No</IsGroup>
      </Category>
      <Category>
        <CategoryName>Tiruchirapalli</CategoryName>
        <IsPinned>No</IsPinned>
        <IsGroup>No</IsGroup>
      </Category>
    </Group>
  </Category>
</ListOfCategories>